algo/__init__.py
algo/call_numpy/__init__.py
algo/call_numpy/call_numpy.cp313-win_amd64.pyd
algo/call_pandas/__init__.py
algo/call_pandas/call_pandas.cp313-win_amd64.pyd
algo/cext/__init__.py
algo/cext/fastsum.cp313-win_amd64.pyd
algo/func01/__init__.py
algo/func01/func01.cp313-win_amd64.pyd
algo/func02/__init__.py
algo/func02/func02.cp313-win_amd64.pyd
test_code/test_code.py
tzuping_algo-0.1.4.dist-info/METADATA
tzuping_algo-0.1.4.dist-info/WHEEL
tzuping_algo-0.1.4.dist-info/top_level.txt
tzuping_algo-0.1.4.dist-info/RECORD
