Metadata-Version: 2.4
Name: tzuping-algo
Version: 0.1.4
Summary: Example algo package with Cython-compiled submodules
Author: Your Name
Classifier: Programming Language :: Python :: 3
Classifier: Programming Language :: Cython
Classifier: Programming Language :: C
Requires-Python: >=3.11
Requires-Dist: pandas>=2.2.3
Requires-Dist: numpy>=2.0.1
